plotshapes/__init__.py
plotshapes/conic_sections.py
plotshapes/quadrilateral.py
plotshapes/transform.py
plot_shapes-0.0.3.dist-info/LICENSE
plot_shapes-0.0.3.dist-info/METADATA
plot_shapes-0.0.3.dist-info/WHEEL
plot_shapes-0.0.3.dist-info/top_level.txt
plot_shapes-0.0.3.dist-info/RECORD
